bw_temporalis/__init__.py
bw_temporalis/convolution.py
bw_temporalis/lca.py
bw_temporalis/temporal_distribution.py
bw_temporalis/timeline.py
bw_temporalis/utils.py
bw_temporalis/lcia/__init__.py
bw_temporalis/lcia/climate.py
bw_temporalis-1.2.0.dist-info/licenses/LICENSE
docs/conf.py
examples/__init__.py
examples/ia.py
examples/inv.py
bw_temporalis-1.2.0.dist-info/METADATA
bw_temporalis-1.2.0.dist-info/WHEEL
bw_temporalis-1.2.0.dist-info/top_level.txt
bw_temporalis-1.2.0.dist-info/RECORD
