Metadata-Version: 2.4
Name: bw_temporalis
Version: 1.2.0
Summary: Revision of bw2temporalis for modern Brightway
Home-page: https://github.com/brightway-lca/bw_temporalis
Author: Chris Mutel
Author-email: <cmutel@gmail.com>
Maintainer: Chris Mutel
Maintainer-email: <cmutel@gmail.com>
License: BSD-3-Clause
Project-URL: source, https://github.com/brightway-lca/bw_temporalis
Project-URL: homepage, https://github.com/brightway-lca/bw_temporalis
Project-URL: tracker, https://github.com/brightway-lca/bw_temporalis/issues
Keywords: "brightway","development"
Platform: any
Classifier: Development Status :: 4 - Beta
Classifier: Programming Language :: Python
Classifier: Programming Language :: Python :: 3
Classifier: Programming Language :: Python :: 3.8
Classifier: Programming Language :: Python :: 3.9
Classifier: Programming Language :: Python :: 3.10
Classifier: Programming Language :: Python :: 3.11
Requires-Python: >=3.8
License-File: LICENSE
Requires-Dist: bw2calc>=2.0.dev13
Requires-Dist: bw2data>=4.0.dev32
Requires-Dist: bw_graph_tools
Requires-Dist: numpy
Requires-Dist: pandas
Requires-Dist: scipy
Requires-Dist: tqdm
Provides-Extra: testing
Requires-Dist: setuptools; extra == "testing"
Requires-Dist: pytest; extra == "testing"
Requires-Dist: pytest-cov; extra == "testing"
Provides-Extra: dev
Requires-Dist: pre-commit; extra == "dev"
Requires-Dist: pylint; extra == "dev"
Provides-Extra: docs
Requires-Dist: sphinx; extra == "docs"
Requires-Dist: myst_parser; extra == "docs"
Requires-Dist: furo; extra == "docs"
Dynamic: license-file
